myamasingcode.py
myamasingcode-0.1.0.dist-info/METADATA
myamasingcode-0.1.0.dist-info/WHEEL
myamasingcode-0.1.0.dist-info/RECORD
