Metadata-Version: 2.1
Name: myamasingcode
Version: 0.1.0
Summary: 
Author: fi
Requires-Python: >=3.12,<4.0
Classifier: Programming Language :: Python :: 3
Classifier: Programming Language :: Python :: 3.12
Requires-Dist: fastapi (==0.87.0)
Requires-Dist: httpx (==0.23.1)
Requires-Dist: loguru (==0.6.0)
Requires-Dist: mysqlclient (>=2.2.4,<3.0.0)
Requires-Dist: numpy (>=1.26.4,<2.0.0)
Requires-Dist: psycopg2-binary (>=2.9.9,<3.0.0)
Requires-Dist: pydantic (==1.10.2)
Requires-Dist: python-dotenv (==0.21.0)
Requires-Dist: python-multipart (==0.0.5)
Requires-Dist: pyyaml (==6.0.1)
Requires-Dist: starlette (==0.21.0)
Requires-Dist: uvicorn (==0.20.0)
